cmlidar/__init__.py
cmlidar/cm.py
cmlidar/rgb/backscatter-rgb.csv
cmlidar/rgb/backscatter_18-rgb.csv
cmlidar/rgb/backscatter_242-rgb.csv
cmlidar/rgb/colorratio-rgb.csv
cmlidar/rgb/colorratio_9-rgb.csv
cmlidar/rgb/depol-rgb.csv
cmlidar/rgb/depol_8-rgb.csv
cmlidar-1.2.3.dist-info/licenses/LICENSE.txt
cmlidar-1.2.3.dist-info/METADATA
cmlidar-1.2.3.dist-info/WHEEL
cmlidar-1.2.3.dist-info/top_level.txt
cmlidar-1.2.3.dist-info/RECORD
