Metadata-Version: 2.4
Name: cmlidar
Version: 1.2.3
License-File: LICENSE.txt
Requires-Dist: matplotlib
Requires-Dist: numpy
Dynamic: license-file
Dynamic: requires-dist
